_editdistance_s.abi3.so
editdistance_s.py
editdistance_s-1.0.0.dist-info/LICENSE
editdistance_s-1.0.0.dist-info/METADATA
editdistance_s-1.0.0.dist-info/WHEEL
editdistance_s-1.0.0.dist-info/top_level.txt
editdistance_s-1.0.0.dist-info/RECORD
